{"authorDailyContributionsMap":{"mathanmahe":[{"date":"2022-01-18","commitResults":[{"hash":"71ec8ba5f4b4ad3411b6260b36a1846a3fdc5a4e","messageTitle":"Level-0","messageBody":"","tags":["Level-0"],"fileTypesAndContributionMap":{"java":{"insertions":8,"deletions":1}}}]},{"date":"2022-01-25","commitResults":[{"hash":"aa6982db4840eaa18863de8cf3cf9cb38c4ef6c4","messageTitle":"Level-1","messageBody":"","tags":["Level-1"],"fileTypesAndContributionMap":{"java":{"insertions":20,"deletions":6}}},{"hash":"f9f7ab67ab4065ba0e194599e7ea0a32f4f6494a","messageTitle":"Level-2","messageBody":"","tags":["Level-2"],"fileTypesAndContributionMap":{"java":{"insertions":14,"deletions":1}}},{"hash":"f688739f7f2800653cda47ed957ca76de7d5b8d2","messageTitle":"Level-3","messageBody":"","tags":["Level-3"],"fileTypesAndContributionMap":{"java":{"insertions":53,"deletions":4}}},{"hash":"5a2712d33e7436962e9d53f00df4b5b1c2ec96d7","messageTitle":"A-CodingStandard","messageBody":"","tags":["A-CodingStandard"],"fileTypesAndContributionMap":{"java":{"insertions":13,"deletions":18}}}]},{"date":"2022-02-01","commitResults":[{"hash":"a6a0cbf169da00c2d69b583c92c5e70b44b76ade","messageTitle":"Level-4","messageBody":"","tags":["Level-4"],"fileTypesAndContributionMap":{"java":{"insertions":126,"deletions":28}}},{"hash":"39d877b56d7efa5d922506c5fbfb4bbbbbba4742","messageTitle":"A-TextUiTesting","messageBody":"","tags":["A-TextUiTesting"],"fileTypesAndContributionMap":{"txt":{"insertions":5,"deletions":0},"java":{"insertions":3,"deletions":3},"bat":{"insertions":1,"deletions":1},"sh":{"insertions":1,"deletions":1}}},{"hash":"cea65b450d0a4c5e01d45814e526fc49a4a3018b","messageTitle":"A-CodeQuality","messageBody":"","tags":["A-CodeQuality"],"fileTypesAndContributionMap":{"txt":{"insertions":9,"deletions":0},"java":{"insertions":108,"deletions":79}}}]}]},"authorFileTypeContributionMap":{"mathanmahe":{"java":206,"md":0,"fxml":0,"sh":1,"bat":1,"gradle":0,"txt":14}},"authorContributionVariance":{"mathanmahe":7191.0903},"authorDisplayNameMap":{"mathanmahe":"F10-4 MATH..DRAN"}}
