[{"path":"src/main/java/Duke.java","fileType":"java","lines":[{"lineNumber":1,"author":{"gitId":"ngys117"},"content":"import java.util.Scanner;","lastModifiedDate":"2022-01-23"},{"lineNumber":2,"author":{"gitId":"ngys117"},"content":"","lastModifiedDate":"2022-01-23"},{"lineNumber":3,"author":{"gitId":"-"},"content":"public class Duke {","lastModifiedDate":"2019-07-29"},{"lineNumber":4,"author":{"gitId":"ngys117"},"content":"    public static void storeInput() {","lastModifiedDate":"2022-01-23"},{"lineNumber":5,"author":{"gitId":"ngys117"},"content":"        String line;","lastModifiedDate":"2022-01-23"},{"lineNumber":6,"author":{"gitId":"ngys117"},"content":"        Scanner in \u003d new Scanner(System.in);","lastModifiedDate":"2022-01-23"},{"lineNumber":7,"author":{"gitId":"ngys117"},"content":"        Task[] tasks \u003d new Task[100];","lastModifiedDate":"2022-01-23"},{"lineNumber":8,"author":{"gitId":"ngys117"},"content":"","lastModifiedDate":"2022-01-23"},{"lineNumber":9,"author":{"gitId":"ngys117"},"content":"        System.out.println(\"Storing Up to 100 Tasks, type list to show all tasks,mark or unmark to set task status\"","lastModifiedDate":"2022-01-23"},{"lineNumber":10,"author":{"gitId":"ngys117"},"content":"                + \" and bye to exit\");","lastModifiedDate":"2022-01-23"},{"lineNumber":11,"author":{"gitId":"ngys117"},"content":"","lastModifiedDate":"2022-01-23"},{"lineNumber":12,"author":{"gitId":"ngys117"},"content":"        do {","lastModifiedDate":"2022-01-23"},{"lineNumber":13,"author":{"gitId":"ngys117"},"content":"            System.out.println(\"Waiting for your input\");","lastModifiedDate":"2022-01-23"},{"lineNumber":14,"author":{"gitId":"ngys117"},"content":"            line \u003d in.nextLine();","lastModifiedDate":"2022-01-23"},{"lineNumber":15,"author":{"gitId":"ngys117"},"content":"            String[] words \u003d line.toLowerCase().split(\" \");","lastModifiedDate":"2022-01-23"},{"lineNumber":16,"author":{"gitId":"ngys117"},"content":"            int taskNumber \u003d 0;","lastModifiedDate":"2022-01-23"},{"lineNumber":17,"author":{"gitId":"ngys117"},"content":"","lastModifiedDate":"2022-01-23"},{"lineNumber":18,"author":{"gitId":"ngys117"},"content":"            switch (words[0]) {","lastModifiedDate":"2022-01-23"},{"lineNumber":19,"author":{"gitId":"ngys117"},"content":"            case \"list\":","lastModifiedDate":"2022-01-23"},{"lineNumber":20,"author":{"gitId":"ngys117"},"content":"                printTasks(tasks);","lastModifiedDate":"2022-01-23"},{"lineNumber":21,"author":{"gitId":"ngys117"},"content":"                break;","lastModifiedDate":"2022-01-23"},{"lineNumber":22,"author":{"gitId":"ngys117"},"content":"            case \"mark\":","lastModifiedDate":"2022-01-23"},{"lineNumber":23,"author":{"gitId":"ngys117"},"content":"                try {","lastModifiedDate":"2022-01-27"},{"lineNumber":24,"author":{"gitId":"ngys117"},"content":"                    if (words.length \u003d\u003d 2) {","lastModifiedDate":"2022-01-23"},{"lineNumber":25,"author":{"gitId":"ngys117"},"content":"                        taskNumber \u003d Integer.parseInt(words[1]);","lastModifiedDate":"2022-01-23"},{"lineNumber":26,"author":{"gitId":"ngys117"},"content":"                    }","lastModifiedDate":"2022-01-23"},{"lineNumber":27,"author":{"gitId":"ngys117"},"content":"                    if (taskNumber \u003e Task.getNumOfTasks()) {","lastModifiedDate":"2022-01-23"},{"lineNumber":28,"author":{"gitId":"ngys117"},"content":"                        System.out.println(\"You don\u0027t have that many tasks \u003e\u003c!\");","lastModifiedDate":"2022-01-23"},{"lineNumber":29,"author":{"gitId":"ngys117"},"content":"                        break;","lastModifiedDate":"2022-01-23"},{"lineNumber":30,"author":{"gitId":"ngys117"},"content":"                    }","lastModifiedDate":"2022-01-23"},{"lineNumber":31,"author":{"gitId":"ngys117"},"content":"                    tasks[taskNumber - 1].setDone();","lastModifiedDate":"2022-01-23"},{"lineNumber":32,"author":{"gitId":"ngys117"},"content":"                    System.out.println(\"I have marked the task as done!\");","lastModifiedDate":"2022-01-23"},{"lineNumber":33,"author":{"gitId":"ngys117"},"content":"                    System.out.println(tasks[taskNumber - 1].getStatusIcon() + tasks[taskNumber - 1].getTaskDescription());","lastModifiedDate":"2022-01-23"},{"lineNumber":34,"author":{"gitId":"ngys117"},"content":"                }","lastModifiedDate":"2022-01-27"},{"lineNumber":35,"author":{"gitId":"ngys117"},"content":"                catch (Exception e) {","lastModifiedDate":"2022-01-27"},{"lineNumber":36,"author":{"gitId":"ngys117"},"content":"                    System.out.println(\"Please enter a number after mark\");","lastModifiedDate":"2022-01-27"},{"lineNumber":37,"author":{"gitId":"ngys117"},"content":"                }","lastModifiedDate":"2022-01-27"},{"lineNumber":38,"author":{"gitId":"ngys117"},"content":"                break;","lastModifiedDate":"2022-01-23"},{"lineNumber":39,"author":{"gitId":"ngys117"},"content":"            case \"unmark\":","lastModifiedDate":"2022-01-23"},{"lineNumber":40,"author":{"gitId":"ngys117"},"content":"                try {","lastModifiedDate":"2022-01-27"},{"lineNumber":41,"author":{"gitId":"ngys117"},"content":"                    if (words.length \u003d\u003d 2) {","lastModifiedDate":"2022-01-23"},{"lineNumber":42,"author":{"gitId":"ngys117"},"content":"                        taskNumber \u003d Integer.parseInt(words[1]);","lastModifiedDate":"2022-01-23"},{"lineNumber":43,"author":{"gitId":"ngys117"},"content":"                    }","lastModifiedDate":"2022-01-23"},{"lineNumber":44,"author":{"gitId":"ngys117"},"content":"                    if (taskNumber \u003e Task.getNumOfTasks()) {","lastModifiedDate":"2022-01-23"},{"lineNumber":45,"author":{"gitId":"ngys117"},"content":"                        System.out.println(\"You don\u0027t have that many tasks \u003e\u003c!\");","lastModifiedDate":"2022-01-23"},{"lineNumber":46,"author":{"gitId":"ngys117"},"content":"                        break;","lastModifiedDate":"2022-01-23"},{"lineNumber":47,"author":{"gitId":"ngys117"},"content":"                    }","lastModifiedDate":"2022-01-23"},{"lineNumber":48,"author":{"gitId":"ngys117"},"content":"                    tasks[taskNumber - 1].setUndone();","lastModifiedDate":"2022-01-23"},{"lineNumber":49,"author":{"gitId":"ngys117"},"content":"                    System.out.println(\"I have marked the task as not done!\");","lastModifiedDate":"2022-01-23"},{"lineNumber":50,"author":{"gitId":"ngys117"},"content":"                    System.out.println(tasks[taskNumber - 1].getStatusIcon() + tasks[taskNumber - 1].getTaskDescription());","lastModifiedDate":"2022-01-23"},{"lineNumber":51,"author":{"gitId":"ngys117"},"content":"                }","lastModifiedDate":"2022-01-27"},{"lineNumber":52,"author":{"gitId":"ngys117"},"content":"                catch (Exception e) {","lastModifiedDate":"2022-01-27"},{"lineNumber":53,"author":{"gitId":"ngys117"},"content":"                    System.out.println(\"Please enter a number after unmark\");","lastModifiedDate":"2022-01-27"},{"lineNumber":54,"author":{"gitId":"ngys117"},"content":"                }","lastModifiedDate":"2022-01-27"},{"lineNumber":55,"author":{"gitId":"ngys117"},"content":"                break;","lastModifiedDate":"2022-01-23"},{"lineNumber":56,"author":{"gitId":"ngys117"},"content":"            default:","lastModifiedDate":"2022-01-23"},{"lineNumber":57,"author":{"gitId":"ngys117"},"content":"                int numOfTasks \u003d Task.getNumOfTasks();","lastModifiedDate":"2022-01-23"},{"lineNumber":58,"author":{"gitId":"ngys117"},"content":"                tasks[numOfTasks] \u003d new Task(line);","lastModifiedDate":"2022-01-23"},{"lineNumber":59,"author":{"gitId":"ngys117"},"content":"                break;","lastModifiedDate":"2022-01-23"},{"lineNumber":60,"author":{"gitId":"ngys117"},"content":"            }","lastModifiedDate":"2022-01-23"},{"lineNumber":61,"author":{"gitId":"ngys117"},"content":"        } while ((!line.equalsIgnoreCase(\"bye\")) \u0026\u0026 Task.getNumOfTasks() \u003c 100);","lastModifiedDate":"2022-01-23"},{"lineNumber":62,"author":{"gitId":"ngys117"},"content":"    }","lastModifiedDate":"2022-01-23"},{"lineNumber":63,"author":{"gitId":"ngys117"},"content":"","lastModifiedDate":"2022-01-23"},{"lineNumber":64,"author":{"gitId":"ngys117"},"content":"    public static void printTasks(Task[] tasks) {","lastModifiedDate":"2022-01-23"},{"lineNumber":65,"author":{"gitId":"ngys117"},"content":"        for (int i \u003d 0; i \u003c Task.getNumOfTasks(); i +\u003d 1) {","lastModifiedDate":"2022-01-23"},{"lineNumber":66,"author":{"gitId":"ngys117"},"content":"            System.out.println(i+1 + \". \" + tasks[i].getStatusIcon() + tasks[i].getTaskDescription());","lastModifiedDate":"2022-01-23"},{"lineNumber":67,"author":{"gitId":"ngys117"},"content":"        }","lastModifiedDate":"2022-01-23"},{"lineNumber":68,"author":{"gitId":"ngys117"},"content":"    }","lastModifiedDate":"2022-01-23"},{"lineNumber":69,"author":{"gitId":"ngys117"},"content":"","lastModifiedDate":"2022-01-23"},{"lineNumber":70,"author":{"gitId":"-"},"content":"    public static void main(String[] args) {","lastModifiedDate":"2019-07-29"},{"lineNumber":71,"author":{"gitId":"ngys117"},"content":"        System.out.println(\"____________________________________________________________\\n\"","lastModifiedDate":"2022-01-21"},{"lineNumber":72,"author":{"gitId":"ngys117"},"content":"                + \"Hello, nice to meet you. I\u0027m Yae! (*^▽^*)\\n\"","lastModifiedDate":"2022-01-23"},{"lineNumber":73,"author":{"gitId":"ngys117"},"content":"                + \"What can I do for you?\\n\"","lastModifiedDate":"2022-01-21"},{"lineNumber":74,"author":{"gitId":"ngys117"},"content":"                + \"____________________________________________________________\");","lastModifiedDate":"2022-01-23"},{"lineNumber":75,"author":{"gitId":"ngys117"},"content":"        storeInput();","lastModifiedDate":"2022-01-23"},{"lineNumber":76,"author":{"gitId":"ngys117"},"content":"        System.out.println(\"Goodbye, see you next time!\");","lastModifiedDate":"2022-01-23"},{"lineNumber":77,"author":{"gitId":"-"},"content":"    }","lastModifiedDate":"2019-07-29"},{"lineNumber":78,"author":{"gitId":"-"},"content":"}","lastModifiedDate":"2019-07-29"}],"authorContributionMap":{"ngys117":74,"-":4}},{"path":"src/main/java/Task.java","fileType":"java","lines":[{"lineNumber":1,"author":{"gitId":"ngys117"},"content":"public class Task {","lastModifiedDate":"2022-01-23"},{"lineNumber":2,"author":{"gitId":"ngys117"},"content":"    private final String taskDescription;","lastModifiedDate":"2022-01-23"},{"lineNumber":3,"author":{"gitId":"ngys117"},"content":"    private boolean isDone;","lastModifiedDate":"2022-01-23"},{"lineNumber":4,"author":{"gitId":"ngys117"},"content":"    private static int numOfTasks \u003d 0;","lastModifiedDate":"2022-01-23"},{"lineNumber":5,"author":{"gitId":"ngys117"},"content":"","lastModifiedDate":"2022-01-23"},{"lineNumber":6,"author":{"gitId":"ngys117"},"content":"    public Task(String taskDescription) {","lastModifiedDate":"2022-01-23"},{"lineNumber":7,"author":{"gitId":"ngys117"},"content":"        this.taskDescription \u003d taskDescription;","lastModifiedDate":"2022-01-23"},{"lineNumber":8,"author":{"gitId":"ngys117"},"content":"        this.isDone \u003d false;","lastModifiedDate":"2022-01-23"},{"lineNumber":9,"author":{"gitId":"ngys117"},"content":"        numOfTasks +\u003d 1;","lastModifiedDate":"2022-01-23"},{"lineNumber":10,"author":{"gitId":"ngys117"},"content":"    }","lastModifiedDate":"2022-01-23"},{"lineNumber":11,"author":{"gitId":"ngys117"},"content":"","lastModifiedDate":"2022-01-23"},{"lineNumber":12,"author":{"gitId":"ngys117"},"content":"    public static int getNumOfTasks() {","lastModifiedDate":"2022-01-23"},{"lineNumber":13,"author":{"gitId":"ngys117"},"content":"        return numOfTasks;","lastModifiedDate":"2022-01-23"},{"lineNumber":14,"author":{"gitId":"ngys117"},"content":"    }","lastModifiedDate":"2022-01-23"},{"lineNumber":15,"author":{"gitId":"ngys117"},"content":"","lastModifiedDate":"2022-01-23"},{"lineNumber":16,"author":{"gitId":"ngys117"},"content":"    public String getTaskDescription() {","lastModifiedDate":"2022-01-23"},{"lineNumber":17,"author":{"gitId":"ngys117"},"content":"        return taskDescription;","lastModifiedDate":"2022-01-23"},{"lineNumber":18,"author":{"gitId":"ngys117"},"content":"    }","lastModifiedDate":"2022-01-23"},{"lineNumber":19,"author":{"gitId":"ngys117"},"content":"","lastModifiedDate":"2022-01-23"},{"lineNumber":20,"author":{"gitId":"ngys117"},"content":"    public void setDone() {","lastModifiedDate":"2022-01-23"},{"lineNumber":21,"author":{"gitId":"ngys117"},"content":"        this.isDone \u003d true;","lastModifiedDate":"2022-01-23"},{"lineNumber":22,"author":{"gitId":"ngys117"},"content":"    }","lastModifiedDate":"2022-01-23"},{"lineNumber":23,"author":{"gitId":"ngys117"},"content":"","lastModifiedDate":"2022-01-23"},{"lineNumber":24,"author":{"gitId":"ngys117"},"content":"    public void setUndone() {","lastModifiedDate":"2022-01-23"},{"lineNumber":25,"author":{"gitId":"ngys117"},"content":"        this.isDone \u003d false;","lastModifiedDate":"2022-01-23"},{"lineNumber":26,"author":{"gitId":"ngys117"},"content":"    }","lastModifiedDate":"2022-01-23"},{"lineNumber":27,"author":{"gitId":"ngys117"},"content":"","lastModifiedDate":"2022-01-23"},{"lineNumber":28,"author":{"gitId":"ngys117"},"content":"    public String getStatusIcon() {","lastModifiedDate":"2022-01-23"},{"lineNumber":29,"author":{"gitId":"ngys117"},"content":"        return (isDone ? \"[X] \" : \"[ ] \");","lastModifiedDate":"2022-01-23"},{"lineNumber":30,"author":{"gitId":"ngys117"},"content":"    }","lastModifiedDate":"2022-01-23"},{"lineNumber":31,"author":{"gitId":"ngys117"},"content":"}","lastModifiedDate":"2022-01-23"}],"authorContributionMap":{"ngys117":31}}]
