[{"path":"data/Duke.txt","fileType":"txt","lines":[{"lineNumber":1,"author":{"gitId":"LDerpy"},"content":"T|1|hello|","lastModifiedDate":"2022-02-18"},{"lineNumber":2,"author":{"gitId":"LDerpy"},"content":"D|0|work|tmr","lastModifiedDate":"2022-02-18"}],"authorContributionMap":{"LDerpy":2}},{"path":"src/main/java/Deadline.java","fileType":"java","lines":[{"lineNumber":1,"author":{"gitId":"LDerpy"},"content":"public class Deadline extends Task {","lastModifiedDate":"2022-02-02"},{"lineNumber":2,"author":{"gitId":"LDerpy"},"content":"    private static final String TASK_CODE \u003d \"D\";","lastModifiedDate":"2022-02-18"},{"lineNumber":3,"author":{"gitId":"LDerpy"},"content":"    protected String by;","lastModifiedDate":"2022-02-02"},{"lineNumber":4,"author":{"gitId":"LDerpy"},"content":"","lastModifiedDate":"2022-02-02"},{"lineNumber":5,"author":{"gitId":"LDerpy"},"content":"    public Deadline(String taskDescription, String by) {","lastModifiedDate":"2022-02-02"},{"lineNumber":6,"author":{"gitId":"LDerpy"},"content":"        super(taskDescription);","lastModifiedDate":"2022-02-02"},{"lineNumber":7,"author":{"gitId":"LDerpy"},"content":"        this.by \u003d by;","lastModifiedDate":"2022-02-02"},{"lineNumber":8,"author":{"gitId":"LDerpy"},"content":"    }","lastModifiedDate":"2022-02-02"},{"lineNumber":9,"author":{"gitId":"LDerpy"},"content":"","lastModifiedDate":"2022-02-02"},{"lineNumber":10,"author":{"gitId":"LDerpy"},"content":"    public Deadline(String taskDescription, boolean isCompleted, String by) {","lastModifiedDate":"2022-02-18"},{"lineNumber":11,"author":{"gitId":"LDerpy"},"content":"        super(taskDescription, isCompleted);","lastModifiedDate":"2022-02-18"},{"lineNumber":12,"author":{"gitId":"LDerpy"},"content":"        this.by \u003d by;","lastModifiedDate":"2022-02-18"},{"lineNumber":13,"author":{"gitId":"LDerpy"},"content":"    }","lastModifiedDate":"2022-02-18"},{"lineNumber":14,"author":{"gitId":"LDerpy"},"content":"","lastModifiedDate":"2022-02-18"},{"lineNumber":15,"author":{"gitId":"LDerpy"},"content":"    @Override","lastModifiedDate":"2022-02-18"},{"lineNumber":16,"author":{"gitId":"LDerpy"},"content":"    public String getTaskCode() {","lastModifiedDate":"2022-02-18"},{"lineNumber":17,"author":{"gitId":"LDerpy"},"content":"        return TASK_CODE;","lastModifiedDate":"2022-02-18"},{"lineNumber":18,"author":{"gitId":"LDerpy"},"content":"    }","lastModifiedDate":"2022-02-18"},{"lineNumber":19,"author":{"gitId":"LDerpy"},"content":"","lastModifiedDate":"2022-02-18"},{"lineNumber":20,"author":{"gitId":"LDerpy"},"content":"    @Override","lastModifiedDate":"2022-02-18"},{"lineNumber":21,"author":{"gitId":"LDerpy"},"content":"    public String getExtraInfo() {","lastModifiedDate":"2022-02-18"},{"lineNumber":22,"author":{"gitId":"LDerpy"},"content":"        return this.by;","lastModifiedDate":"2022-02-18"},{"lineNumber":23,"author":{"gitId":"LDerpy"},"content":"    }","lastModifiedDate":"2022-02-18"},{"lineNumber":24,"author":{"gitId":"LDerpy"},"content":"","lastModifiedDate":"2022-02-18"},{"lineNumber":25,"author":{"gitId":"LDerpy"},"content":"    @Override","lastModifiedDate":"2022-02-02"},{"lineNumber":26,"author":{"gitId":"LDerpy"},"content":"    public String toString() {","lastModifiedDate":"2022-02-02"},{"lineNumber":27,"author":{"gitId":"LDerpy"},"content":"        return \"[\" + getTaskCode() + \"]\" + super.toString() + \" (by: \" + by + \")\\n\";","lastModifiedDate":"2022-02-18"},{"lineNumber":28,"author":{"gitId":"LDerpy"},"content":"    }","lastModifiedDate":"2022-02-02"},{"lineNumber":29,"author":{"gitId":"LDerpy"},"content":"}","lastModifiedDate":"2022-02-02"}],"authorContributionMap":{"LDerpy":29}},{"path":"src/main/java/Duke.java","fileType":"java","lines":[{"lineNumber":1,"author":{"gitId":"LDerpy"},"content":"import java.util.Scanner;","lastModifiedDate":"2022-01-28"},{"lineNumber":2,"author":{"gitId":"LDerpy"},"content":"import java.util.ArrayList;","lastModifiedDate":"2022-02-01"},{"lineNumber":3,"author":{"gitId":"LDerpy"},"content":"","lastModifiedDate":"2022-01-28"},{"lineNumber":4,"author":{"gitId":"-"},"content":"public class Duke {","lastModifiedDate":"2019-07-29"},{"lineNumber":5,"author":{"gitId":"-"},"content":"    public static void main(String[] args) {","lastModifiedDate":"2019-07-29"},{"lineNumber":6,"author":{"gitId":"LDerpy"},"content":"        Ui.startDuke();","lastModifiedDate":"2022-02-24"},{"lineNumber":7,"author":{"gitId":"LDerpy"},"content":"","lastModifiedDate":"2022-02-01"},{"lineNumber":8,"author":{"gitId":"LDerpy"},"content":"        Scanner userInput \u003d new Scanner(System.in);","lastModifiedDate":"2022-02-01"},{"lineNumber":9,"author":{"gitId":"LDerpy"},"content":"        String line;","lastModifiedDate":"2022-02-01"},{"lineNumber":10,"author":{"gitId":"LDerpy"},"content":"        TaskList tasks \u003d new TaskList();","lastModifiedDate":"2022-02-24"},{"lineNumber":11,"author":{"gitId":"LDerpy"},"content":"        Storage.storageSetup(tasks);","lastModifiedDate":"2022-02-18"},{"lineNumber":12,"author":{"gitId":"LDerpy"},"content":"        line \u003d userInput.nextLine();","lastModifiedDate":"2022-02-01"},{"lineNumber":13,"author":{"gitId":"LDerpy"},"content":"        while (!\"bye\".equals(line)) {","lastModifiedDate":"2022-02-01"},{"lineNumber":14,"author":{"gitId":"LDerpy"},"content":"            try {","lastModifiedDate":"2022-02-14"},{"lineNumber":15,"author":{"gitId":"LDerpy"},"content":"                Parser parsedInput \u003d new Parser(line);","lastModifiedDate":"2022-02-14"},{"lineNumber":16,"author":{"gitId":"LDerpy"},"content":"                switch (parsedInput.getParsedInput()[0]) {","lastModifiedDate":"2022-02-01"},{"lineNumber":17,"author":{"gitId":"LDerpy"},"content":"                case \"todo\":","lastModifiedDate":"2022-02-02"},{"lineNumber":18,"author":{"gitId":"LDerpy"},"content":"                    line \u003d line.replace(\"todo\",\"\").strip();","lastModifiedDate":"2022-02-14"},{"lineNumber":19,"author":{"gitId":"LDerpy"},"content":"                    Todo newTodo \u003d new Todo(line);","lastModifiedDate":"2022-02-02"},{"lineNumber":20,"author":{"gitId":"LDerpy"},"content":"                    tasks.add(newTodo);","lastModifiedDate":"2022-02-02"},{"lineNumber":21,"author":{"gitId":"LDerpy"},"content":"                    Ui.printTextBetweenLines(\"Added to new thing to do for ya!\\n \" + newTodo);","lastModifiedDate":"2022-02-24"},{"lineNumber":22,"author":{"gitId":"LDerpy"},"content":"                    break;","lastModifiedDate":"2022-02-02"},{"lineNumber":23,"author":{"gitId":"LDerpy"},"content":"                case \"deadline\":","lastModifiedDate":"2022-02-02"},{"lineNumber":24,"author":{"gitId":"LDerpy"},"content":"                    line \u003d line.replace(\"deadline\", \"\");","lastModifiedDate":"2022-02-14"},{"lineNumber":25,"author":{"gitId":"LDerpy"},"content":"                    String deadlineTask \u003d line.substring(0, line.indexOf(\"/by\")).strip();","lastModifiedDate":"2022-02-14"},{"lineNumber":26,"author":{"gitId":"LDerpy"},"content":"                    String by \u003d line.substring(line.indexOf(\"/by\") + 4);","lastModifiedDate":"2022-02-14"},{"lineNumber":27,"author":{"gitId":"LDerpy"},"content":"                    Deadline newDeadline \u003d new Deadline(deadlineTask, by);","lastModifiedDate":"2022-02-02"},{"lineNumber":28,"author":{"gitId":"LDerpy"},"content":"                    tasks.add(newDeadline);","lastModifiedDate":"2022-02-02"},{"lineNumber":29,"author":{"gitId":"LDerpy"},"content":"                    Ui.printTextBetweenLines(\"Added to thing for ya, and ya gotta do it soon!\\n \" + newDeadline);","lastModifiedDate":"2022-02-24"},{"lineNumber":30,"author":{"gitId":"LDerpy"},"content":"                    break;","lastModifiedDate":"2022-02-02"},{"lineNumber":31,"author":{"gitId":"LDerpy"},"content":"                case \"event\":","lastModifiedDate":"2022-02-02"},{"lineNumber":32,"author":{"gitId":"LDerpy"},"content":"                    String eventTask \u003d line.substring(6, line.indexOf(\"/\") - 1);","lastModifiedDate":"2022-02-02"},{"lineNumber":33,"author":{"gitId":"LDerpy"},"content":"                    String at \u003d line.substring(line.indexOf(\"/at\") + 4);","lastModifiedDate":"2022-02-14"},{"lineNumber":34,"author":{"gitId":"LDerpy"},"content":"                    Event newEvent \u003d new Event(eventTask, at);","lastModifiedDate":"2022-02-02"},{"lineNumber":35,"author":{"gitId":"LDerpy"},"content":"                    tasks.add(newEvent);","lastModifiedDate":"2022-02-02"},{"lineNumber":36,"author":{"gitId":"LDerpy"},"content":"                    Ui.printTextBetweenLines(\"Added to thing for ya at some place and time!\\n \" + newEvent);","lastModifiedDate":"2022-02-24"},{"lineNumber":37,"author":{"gitId":"LDerpy"},"content":"                    break;","lastModifiedDate":"2022-02-02"},{"lineNumber":38,"author":{"gitId":"LDerpy"},"content":"                case \"list\":","lastModifiedDate":"2022-02-01"},{"lineNumber":39,"author":{"gitId":"LDerpy"},"content":"                    String allTasks \u003d \"\";","lastModifiedDate":"2022-02-01"},{"lineNumber":40,"author":{"gitId":"LDerpy"},"content":"                    for (int i \u003d 0; i \u003c tasks.size(); i++) {","lastModifiedDate":"2022-02-01"},{"lineNumber":41,"author":{"gitId":"LDerpy"},"content":"                        allTasks \u003d allTasks + \" \" + (i + 1) + \". \" + tasks.get(i).toString();","lastModifiedDate":"2022-02-01"},{"lineNumber":42,"author":{"gitId":"LDerpy"},"content":"                    }","lastModifiedDate":"2022-02-01"},{"lineNumber":43,"author":{"gitId":"LDerpy"},"content":"                    Ui.printTextBetweenLines(allTasks);","lastModifiedDate":"2022-02-24"},{"lineNumber":44,"author":{"gitId":"LDerpy"},"content":"                    break;","lastModifiedDate":"2022-02-01"},{"lineNumber":45,"author":{"gitId":"LDerpy"},"content":"                case \"mark\":","lastModifiedDate":"2022-02-01"},{"lineNumber":46,"author":{"gitId":"LDerpy"},"content":"                    int taskIndex \u003d Integer.parseInt(parsedInput.getParsedInput()[1]) - 1;","lastModifiedDate":"2022-02-14"},{"lineNumber":47,"author":{"gitId":"LDerpy"},"content":"                    tasks.get(taskIndex).setCompleted(true);","lastModifiedDate":"2022-02-18"},{"lineNumber":48,"author":{"gitId":"LDerpy"},"content":"                    Ui.printTextBetweenLines(\"Marked this task as done!\\n \" + tasks.get(taskIndex).toString());","lastModifiedDate":"2022-02-24"},{"lineNumber":49,"author":{"gitId":"LDerpy"},"content":"                    break;","lastModifiedDate":"2022-02-01"},{"lineNumber":50,"author":{"gitId":"LDerpy"},"content":"                case \"unmark\":","lastModifiedDate":"2022-02-01"},{"lineNumber":51,"author":{"gitId":"LDerpy"},"content":"                    taskIndex \u003d Integer.parseInt(parsedInput.getParsedInput()[1]) - 1;","lastModifiedDate":"2022-02-14"},{"lineNumber":52,"author":{"gitId":"LDerpy"},"content":"                    tasks.get(taskIndex).setCompleted(false);","lastModifiedDate":"2022-02-18"},{"lineNumber":53,"author":{"gitId":"LDerpy"},"content":"                    Ui.printTextBetweenLines(\"Guess you messed up huh? Reverted that task!\\n \" + tasks.get(taskIndex).toString());","lastModifiedDate":"2022-02-24"},{"lineNumber":54,"author":{"gitId":"LDerpy"},"content":"                    break;","lastModifiedDate":"2022-02-01"},{"lineNumber":55,"author":{"gitId":"LDerpy"},"content":"                case \"delete\":","lastModifiedDate":"2022-02-18"},{"lineNumber":56,"author":{"gitId":"LDerpy"},"content":"                    taskIndex \u003d Integer.parseInt(parsedInput.getParsedInput()[1]) - 1;","lastModifiedDate":"2022-02-18"},{"lineNumber":57,"author":{"gitId":"LDerpy"},"content":"                    Ui.printTextBetweenLines(\"Either you\u0027re done with that task or gave up. Anyways its gone!\\n \" + tasks.get(taskIndex).toString());","lastModifiedDate":"2022-02-24"},{"lineNumber":58,"author":{"gitId":"LDerpy"},"content":"                    tasks.remove(taskIndex);","lastModifiedDate":"2022-02-18"},{"lineNumber":59,"author":{"gitId":"LDerpy"},"content":"                    break;","lastModifiedDate":"2022-02-18"},{"lineNumber":60,"author":{"gitId":"LDerpy"},"content":"                }","lastModifiedDate":"2022-02-01"},{"lineNumber":61,"author":{"gitId":"LDerpy"},"content":"            } catch (InvalidCommandException e) {","lastModifiedDate":"2022-02-14"},{"lineNumber":62,"author":{"gitId":"LDerpy"},"content":"                Ui.printTextBetweenLines(\"Whoopsies! I dont know what you\u0027re talking about! Try again!\\n\");","lastModifiedDate":"2022-02-24"},{"lineNumber":63,"author":{"gitId":"LDerpy"},"content":"            } catch (MissingDescriptionException e) {","lastModifiedDate":"2022-02-14"},{"lineNumber":64,"author":{"gitId":"LDerpy"},"content":"                Ui.printTextBetweenLines(\"I think you forgot some stuff there for that command! Try again!\\n\");","lastModifiedDate":"2022-02-24"},{"lineNumber":65,"author":{"gitId":"LDerpy"},"content":"            }","lastModifiedDate":"2022-02-01"},{"lineNumber":66,"author":{"gitId":"LDerpy"},"content":"            System.out.println();","lastModifiedDate":"2022-02-01"},{"lineNumber":67,"author":{"gitId":"LDerpy"},"content":"            line \u003d userInput.nextLine();","lastModifiedDate":"2022-02-01"},{"lineNumber":68,"author":{"gitId":"LDerpy"},"content":"        }","lastModifiedDate":"2022-02-01"},{"lineNumber":69,"author":{"gitId":"LDerpy"},"content":"        Storage.writeTasksToFile(tasks);","lastModifiedDate":"2022-02-18"},{"lineNumber":70,"author":{"gitId":"LDerpy"},"content":"        Ui.endDuke();","lastModifiedDate":"2022-02-24"},{"lineNumber":71,"author":{"gitId":"-"},"content":"    }","lastModifiedDate":"2019-07-29"},{"lineNumber":72,"author":{"gitId":"-"},"content":"}","lastModifiedDate":"2019-07-29"}],"authorContributionMap":{"LDerpy":68,"-":4}},{"path":"src/main/java/Event.java","fileType":"java","lines":[{"lineNumber":1,"author":{"gitId":"LDerpy"},"content":"public class Event extends Task {","lastModifiedDate":"2022-02-02"},{"lineNumber":2,"author":{"gitId":"LDerpy"},"content":"    private static final String TASK_CODE \u003d \"E\";","lastModifiedDate":"2022-02-18"},{"lineNumber":3,"author":{"gitId":"LDerpy"},"content":"    protected String at;","lastModifiedDate":"2022-02-02"},{"lineNumber":4,"author":{"gitId":"LDerpy"},"content":"","lastModifiedDate":"2022-02-02"},{"lineNumber":5,"author":{"gitId":"LDerpy"},"content":"    public Event(String taskDescription, String at) {","lastModifiedDate":"2022-02-02"},{"lineNumber":6,"author":{"gitId":"LDerpy"},"content":"        super(taskDescription);","lastModifiedDate":"2022-02-02"},{"lineNumber":7,"author":{"gitId":"LDerpy"},"content":"        this.at \u003d at;","lastModifiedDate":"2022-02-02"},{"lineNumber":8,"author":{"gitId":"LDerpy"},"content":"    }","lastModifiedDate":"2022-02-02"},{"lineNumber":9,"author":{"gitId":"LDerpy"},"content":"","lastModifiedDate":"2022-02-02"},{"lineNumber":10,"author":{"gitId":"LDerpy"},"content":"    public Event(String taskDescription, boolean isCompleted, String at) {","lastModifiedDate":"2022-02-18"},{"lineNumber":11,"author":{"gitId":"LDerpy"},"content":"        super(taskDescription, isCompleted);","lastModifiedDate":"2022-02-18"},{"lineNumber":12,"author":{"gitId":"LDerpy"},"content":"        this.at \u003d at;","lastModifiedDate":"2022-02-18"},{"lineNumber":13,"author":{"gitId":"LDerpy"},"content":"    }","lastModifiedDate":"2022-02-18"},{"lineNumber":14,"author":{"gitId":"LDerpy"},"content":"","lastModifiedDate":"2022-02-18"},{"lineNumber":15,"author":{"gitId":"LDerpy"},"content":"    @Override","lastModifiedDate":"2022-02-18"},{"lineNumber":16,"author":{"gitId":"LDerpy"},"content":"    public String getTaskCode() {","lastModifiedDate":"2022-02-18"},{"lineNumber":17,"author":{"gitId":"LDerpy"},"content":"        return TASK_CODE;","lastModifiedDate":"2022-02-18"},{"lineNumber":18,"author":{"gitId":"LDerpy"},"content":"    }","lastModifiedDate":"2022-02-18"},{"lineNumber":19,"author":{"gitId":"LDerpy"},"content":"","lastModifiedDate":"2022-02-18"},{"lineNumber":20,"author":{"gitId":"LDerpy"},"content":"    @Override","lastModifiedDate":"2022-02-18"},{"lineNumber":21,"author":{"gitId":"LDerpy"},"content":"    public String getExtraInfo() {","lastModifiedDate":"2022-02-18"},{"lineNumber":22,"author":{"gitId":"LDerpy"},"content":"        return this.at;","lastModifiedDate":"2022-02-18"},{"lineNumber":23,"author":{"gitId":"LDerpy"},"content":"    }","lastModifiedDate":"2022-02-18"},{"lineNumber":24,"author":{"gitId":"LDerpy"},"content":"","lastModifiedDate":"2022-02-18"},{"lineNumber":25,"author":{"gitId":"LDerpy"},"content":"    @Override","lastModifiedDate":"2022-02-02"},{"lineNumber":26,"author":{"gitId":"LDerpy"},"content":"    public String toString() {","lastModifiedDate":"2022-02-02"},{"lineNumber":27,"author":{"gitId":"LDerpy"},"content":"        return \"[\" + getTaskCode() + \"]\" + super.toString() + \" (at: \" + at + \")\\n\";","lastModifiedDate":"2022-02-18"},{"lineNumber":28,"author":{"gitId":"LDerpy"},"content":"    }","lastModifiedDate":"2022-02-02"},{"lineNumber":29,"author":{"gitId":"LDerpy"},"content":"}","lastModifiedDate":"2022-02-02"}],"authorContributionMap":{"LDerpy":29}},{"path":"src/main/java/InvalidCommandException.java","fileType":"java","lines":[{"lineNumber":1,"author":{"gitId":"LDerpy"},"content":"/**","lastModifiedDate":"2022-02-14"},{"lineNumber":2,"author":{"gitId":"LDerpy"},"content":" * InvalidCommandException is thrown when a command is entered","lastModifiedDate":"2022-02-14"},{"lineNumber":3,"author":{"gitId":"LDerpy"},"content":" * with an input that does not match available commands.","lastModifiedDate":"2022-02-14"},{"lineNumber":4,"author":{"gitId":"LDerpy"},"content":" */","lastModifiedDate":"2022-02-14"},{"lineNumber":5,"author":{"gitId":"LDerpy"},"content":"public class InvalidCommandException extends Exception {","lastModifiedDate":"2022-02-14"},{"lineNumber":6,"author":{"gitId":"LDerpy"},"content":"}","lastModifiedDate":"2022-02-14"}],"authorContributionMap":{"LDerpy":6}},{"path":"src/main/java/Message.java","fileType":"java","lines":[{"lineNumber":1,"author":{"gitId":"LDerpy"},"content":"public class Message {","lastModifiedDate":"2022-02-24"},{"lineNumber":2,"author":{"gitId":"LDerpy"},"content":"    public static final String HORIZONTAL_LINE \u003d \"__________________________________________________\";","lastModifiedDate":"2022-02-24"},{"lineNumber":3,"author":{"gitId":"LDerpy"},"content":"    public static final String GREET_MESSAGE \u003d","lastModifiedDate":"2022-02-24"},{"lineNumber":4,"author":{"gitId":"LDerpy"},"content":"            \" ____        _        \\n\"","lastModifiedDate":"2022-02-24"},{"lineNumber":5,"author":{"gitId":"LDerpy"},"content":"            + \"|  _ \\\\ _   _| | _____ \\n\"","lastModifiedDate":"2022-02-24"},{"lineNumber":6,"author":{"gitId":"LDerpy"},"content":"            + \"| | | | | | | |/ / _ \\\\\\n\"","lastModifiedDate":"2022-02-24"},{"lineNumber":7,"author":{"gitId":"LDerpy"},"content":"            + \"| |_| | |_| |   \u003c  __/\\n\"","lastModifiedDate":"2022-02-24"},{"lineNumber":8,"author":{"gitId":"LDerpy"},"content":"            + \"|____/ \\\\__,_|_|\\\\_\\\\___|\\n\"","lastModifiedDate":"2022-02-24"},{"lineNumber":9,"author":{"gitId":"LDerpy"},"content":"            + \"__________________________________________________\\n\"","lastModifiedDate":"2022-02-24"},{"lineNumber":10,"author":{"gitId":"LDerpy"},"content":"            + \"Hello! Duke here!\\n\"","lastModifiedDate":"2022-02-24"},{"lineNumber":11,"author":{"gitId":"LDerpy"},"content":"            + \"How can I help?\\n\"","lastModifiedDate":"2022-02-24"},{"lineNumber":12,"author":{"gitId":"LDerpy"},"content":"            + \"__________________________________________________\\n\";","lastModifiedDate":"2022-02-24"},{"lineNumber":13,"author":{"gitId":"LDerpy"},"content":"","lastModifiedDate":"2022-02-24"},{"lineNumber":14,"author":{"gitId":"LDerpy"},"content":"    public static final String GOODBYE_MESSAGE \u003d \"\\t Goodbye. See you next time!\";","lastModifiedDate":"2022-02-24"},{"lineNumber":15,"author":{"gitId":"LDerpy"},"content":"","lastModifiedDate":"2022-02-24"},{"lineNumber":16,"author":{"gitId":"LDerpy"},"content":"}","lastModifiedDate":"2022-02-24"}],"authorContributionMap":{"LDerpy":16}},{"path":"src/main/java/MissingDescriptionException.java","fileType":"java","lines":[{"lineNumber":1,"author":{"gitId":"LDerpy"},"content":"/**","lastModifiedDate":"2022-02-14"},{"lineNumber":2,"author":{"gitId":"LDerpy"},"content":" * MissingDescriptionException is thrown when correct commands are used","lastModifiedDate":"2022-02-14"},{"lineNumber":3,"author":{"gitId":"LDerpy"},"content":" * but are missing vital descriptions for the method to work properly.","lastModifiedDate":"2022-02-14"},{"lineNumber":4,"author":{"gitId":"LDerpy"},"content":" */","lastModifiedDate":"2022-02-14"},{"lineNumber":5,"author":{"gitId":"LDerpy"},"content":"public class MissingDescriptionException extends Exception {","lastModifiedDate":"2022-02-14"},{"lineNumber":6,"author":{"gitId":"LDerpy"},"content":"}","lastModifiedDate":"2022-02-14"}],"authorContributionMap":{"LDerpy":6}},{"path":"src/main/java/Parser.java","fileType":"java","lines":[{"lineNumber":1,"author":{"gitId":"LDerpy"},"content":"public class Parser {","lastModifiedDate":"2022-02-14"},{"lineNumber":2,"author":{"gitId":"LDerpy"},"content":"    private String[] parsedInput;","lastModifiedDate":"2022-02-01"},{"lineNumber":3,"author":{"gitId":"LDerpy"},"content":"","lastModifiedDate":"2022-02-01"},{"lineNumber":4,"author":{"gitId":"LDerpy"},"content":"    public Parser(String line) throws InvalidCommandException, MissingDescriptionException {","lastModifiedDate":"2022-02-14"},{"lineNumber":5,"author":{"gitId":"LDerpy"},"content":"        parsedInput \u003d line.split(\" \");","lastModifiedDate":"2022-02-01"},{"lineNumber":6,"author":{"gitId":"LDerpy"},"content":"","lastModifiedDate":"2022-02-01"},{"lineNumber":7,"author":{"gitId":"LDerpy"},"content":"        switch (parsedInput[0]) {","lastModifiedDate":"2022-02-01"},{"lineNumber":8,"author":{"gitId":"LDerpy"},"content":"        case \"todo\":","lastModifiedDate":"2022-02-02"},{"lineNumber":9,"author":{"gitId":"LDerpy"},"content":"            if (parsedInput.length \u003c 2) {","lastModifiedDate":"2022-02-14"},{"lineNumber":10,"author":{"gitId":"LDerpy"},"content":"                throw new MissingDescriptionException();","lastModifiedDate":"2022-02-14"},{"lineNumber":11,"author":{"gitId":"LDerpy"},"content":"            }","lastModifiedDate":"2022-02-14"},{"lineNumber":12,"author":{"gitId":"LDerpy"},"content":"            break;","lastModifiedDate":"2022-02-14"},{"lineNumber":13,"author":{"gitId":"LDerpy"},"content":"        case \"deadline\":","lastModifiedDate":"2022-02-02"},{"lineNumber":14,"author":{"gitId":"LDerpy"},"content":"            // Fallthrough","lastModifiedDate":"2022-02-02"},{"lineNumber":15,"author":{"gitId":"LDerpy"},"content":"        case \"event\":","lastModifiedDate":"2022-02-02"},{"lineNumber":16,"author":{"gitId":"LDerpy"},"content":"            // Fallthrough","lastModifiedDate":"2022-02-02"},{"lineNumber":17,"author":{"gitId":"LDerpy"},"content":"        case \"list\":","lastModifiedDate":"2022-02-01"},{"lineNumber":18,"author":{"gitId":"LDerpy"},"content":"            break;","lastModifiedDate":"2022-02-01"},{"lineNumber":19,"author":{"gitId":"LDerpy"},"content":"        case \"delete\":","lastModifiedDate":"2022-02-18"},{"lineNumber":20,"author":{"gitId":"LDerpy"},"content":"            // Fallthrough","lastModifiedDate":"2022-02-18"},{"lineNumber":21,"author":{"gitId":"LDerpy"},"content":"        case \"mark\":","lastModifiedDate":"2022-02-01"},{"lineNumber":22,"author":{"gitId":"LDerpy"},"content":"            // Fallthrough","lastModifiedDate":"2022-02-01"},{"lineNumber":23,"author":{"gitId":"LDerpy"},"content":"        case \"unmark\":","lastModifiedDate":"2022-02-01"},{"lineNumber":24,"author":{"gitId":"LDerpy"},"content":"            if (parsedInput.length !\u003d 2) { //simple workaround for now, need better checks later","lastModifiedDate":"2022-02-14"},{"lineNumber":25,"author":{"gitId":"LDerpy"},"content":"                throw new MissingDescriptionException();","lastModifiedDate":"2022-02-14"},{"lineNumber":26,"author":{"gitId":"LDerpy"},"content":"            }","lastModifiedDate":"2022-02-01"},{"lineNumber":27,"author":{"gitId":"LDerpy"},"content":"            break;","lastModifiedDate":"2022-02-01"},{"lineNumber":28,"author":{"gitId":"LDerpy"},"content":"        default:","lastModifiedDate":"2022-02-01"},{"lineNumber":29,"author":{"gitId":"LDerpy"},"content":"            throw new InvalidCommandException();","lastModifiedDate":"2022-02-14"},{"lineNumber":30,"author":{"gitId":"LDerpy"},"content":"        }","lastModifiedDate":"2022-02-01"},{"lineNumber":31,"author":{"gitId":"LDerpy"},"content":"    }","lastModifiedDate":"2022-02-01"},{"lineNumber":32,"author":{"gitId":"LDerpy"},"content":"","lastModifiedDate":"2022-02-01"},{"lineNumber":33,"author":{"gitId":"LDerpy"},"content":"    public String[] getParsedInput() {","lastModifiedDate":"2022-02-01"},{"lineNumber":34,"author":{"gitId":"LDerpy"},"content":"        return parsedInput;","lastModifiedDate":"2022-02-01"},{"lineNumber":35,"author":{"gitId":"LDerpy"},"content":"    }","lastModifiedDate":"2022-02-01"},{"lineNumber":36,"author":{"gitId":"LDerpy"},"content":"","lastModifiedDate":"2022-02-01"},{"lineNumber":37,"author":{"gitId":"LDerpy"},"content":"}","lastModifiedDate":"2022-02-01"}],"authorContributionMap":{"LDerpy":37}},{"path":"src/main/java/Storage.java","fileType":"java","lines":[{"lineNumber":1,"author":{"gitId":"LDerpy"},"content":"import java.io.File;","lastModifiedDate":"2022-02-18"},{"lineNumber":2,"author":{"gitId":"LDerpy"},"content":"import java.io.FileNotFoundException;","lastModifiedDate":"2022-02-18"},{"lineNumber":3,"author":{"gitId":"LDerpy"},"content":"import java.io.FileWriter;","lastModifiedDate":"2022-02-18"},{"lineNumber":4,"author":{"gitId":"LDerpy"},"content":"import java.io.IOException;","lastModifiedDate":"2022-02-18"},{"lineNumber":5,"author":{"gitId":"LDerpy"},"content":"import java.util.ArrayList;","lastModifiedDate":"2022-02-18"},{"lineNumber":6,"author":{"gitId":"LDerpy"},"content":"import java.util.Scanner;","lastModifiedDate":"2022-02-18"},{"lineNumber":7,"author":{"gitId":"LDerpy"},"content":"","lastModifiedDate":"2022-02-18"},{"lineNumber":8,"author":{"gitId":"LDerpy"},"content":"public class Storage {","lastModifiedDate":"2022-02-18"},{"lineNumber":9,"author":{"gitId":"LDerpy"},"content":"    private static final String DIRECTORY_NAME \u003d \"data\";","lastModifiedDate":"2022-02-18"},{"lineNumber":10,"author":{"gitId":"LDerpy"},"content":"    private static final String FILE_NAME \u003d \"Duke.txt\";","lastModifiedDate":"2022-02-18"},{"lineNumber":11,"author":{"gitId":"LDerpy"},"content":"","lastModifiedDate":"2022-02-18"},{"lineNumber":12,"author":{"gitId":"LDerpy"},"content":"    public static void storageSetup(TaskList tasks) {","lastModifiedDate":"2022-02-24"},{"lineNumber":13,"author":{"gitId":"LDerpy"},"content":"        File directory \u003d new File(DIRECTORY_NAME);","lastModifiedDate":"2022-02-18"},{"lineNumber":14,"author":{"gitId":"LDerpy"},"content":"        File file \u003d new File(DIRECTORY_NAME + \"/\" + FILE_NAME);","lastModifiedDate":"2022-02-18"},{"lineNumber":15,"author":{"gitId":"LDerpy"},"content":"        if (!directory.exists()) {","lastModifiedDate":"2022-02-18"},{"lineNumber":16,"author":{"gitId":"LDerpy"},"content":"            createDirectory(directory);","lastModifiedDate":"2022-02-18"},{"lineNumber":17,"author":{"gitId":"LDerpy"},"content":"            createFile(file);","lastModifiedDate":"2022-02-18"},{"lineNumber":18,"author":{"gitId":"LDerpy"},"content":"        } else if (!file.exists()) {","lastModifiedDate":"2022-02-18"},{"lineNumber":19,"author":{"gitId":"LDerpy"},"content":"            createFile(file);","lastModifiedDate":"2022-02-18"},{"lineNumber":20,"author":{"gitId":"LDerpy"},"content":"        }","lastModifiedDate":"2022-02-18"},{"lineNumber":21,"author":{"gitId":"LDerpy"},"content":"        try {","lastModifiedDate":"2022-02-18"},{"lineNumber":22,"author":{"gitId":"LDerpy"},"content":"            readTasksFromFile(file, tasks);","lastModifiedDate":"2022-02-18"},{"lineNumber":23,"author":{"gitId":"LDerpy"},"content":"        } catch (FileNotFoundException e) {","lastModifiedDate":"2022-02-18"},{"lineNumber":24,"author":{"gitId":"LDerpy"},"content":"            // Workaround for now until proper ui class is created","lastModifiedDate":"2022-02-18"},{"lineNumber":25,"author":{"gitId":"LDerpy"},"content":"            Ui.printTextBetweenLines(\"\\t File not found!\");","lastModifiedDate":"2022-02-24"},{"lineNumber":26,"author":{"gitId":"LDerpy"},"content":"        }","lastModifiedDate":"2022-02-18"},{"lineNumber":27,"author":{"gitId":"LDerpy"},"content":"    }","lastModifiedDate":"2022-02-18"},{"lineNumber":28,"author":{"gitId":"LDerpy"},"content":"","lastModifiedDate":"2022-02-18"},{"lineNumber":29,"author":{"gitId":"LDerpy"},"content":"    public static void createDirectory(File directory) {","lastModifiedDate":"2022-02-18"},{"lineNumber":30,"author":{"gitId":"LDerpy"},"content":"        try {","lastModifiedDate":"2022-02-18"},{"lineNumber":31,"author":{"gitId":"LDerpy"},"content":"            directory.mkdir();","lastModifiedDate":"2022-02-18"},{"lineNumber":32,"author":{"gitId":"LDerpy"},"content":"        } catch (Exception e) {","lastModifiedDate":"2022-02-18"},{"lineNumber":33,"author":{"gitId":"LDerpy"},"content":"            e.getStackTrace();","lastModifiedDate":"2022-02-18"},{"lineNumber":34,"author":{"gitId":"LDerpy"},"content":"        }","lastModifiedDate":"2022-02-18"},{"lineNumber":35,"author":{"gitId":"LDerpy"},"content":"    }","lastModifiedDate":"2022-02-18"},{"lineNumber":36,"author":{"gitId":"LDerpy"},"content":"","lastModifiedDate":"2022-02-18"},{"lineNumber":37,"author":{"gitId":"LDerpy"},"content":"    public static void createFile(File file) {","lastModifiedDate":"2022-02-18"},{"lineNumber":38,"author":{"gitId":"LDerpy"},"content":"        try {","lastModifiedDate":"2022-02-18"},{"lineNumber":39,"author":{"gitId":"LDerpy"},"content":"            file.createNewFile();","lastModifiedDate":"2022-02-18"},{"lineNumber":40,"author":{"gitId":"LDerpy"},"content":"        } catch (Exception e) {","lastModifiedDate":"2022-02-18"},{"lineNumber":41,"author":{"gitId":"LDerpy"},"content":"            e.getStackTrace();","lastModifiedDate":"2022-02-18"},{"lineNumber":42,"author":{"gitId":"LDerpy"},"content":"        }","lastModifiedDate":"2022-02-18"},{"lineNumber":43,"author":{"gitId":"LDerpy"},"content":"    }","lastModifiedDate":"2022-02-18"},{"lineNumber":44,"author":{"gitId":"LDerpy"},"content":"","lastModifiedDate":"2022-02-18"},{"lineNumber":45,"author":{"gitId":"LDerpy"},"content":"    public static void readTasksFromFile(File file, TaskList tasks) throws FileNotFoundException {","lastModifiedDate":"2022-02-24"},{"lineNumber":46,"author":{"gitId":"LDerpy"},"content":"        Scanner scanner \u003d new Scanner(file);","lastModifiedDate":"2022-02-18"},{"lineNumber":47,"author":{"gitId":"LDerpy"},"content":"        while (scanner.hasNext()) {","lastModifiedDate":"2022-02-18"},{"lineNumber":48,"author":{"gitId":"LDerpy"},"content":"            loadTaskFromFile(tasks, scanner.nextLine());","lastModifiedDate":"2022-02-18"},{"lineNumber":49,"author":{"gitId":"LDerpy"},"content":"        }","lastModifiedDate":"2022-02-18"},{"lineNumber":50,"author":{"gitId":"LDerpy"},"content":"    }","lastModifiedDate":"2022-02-18"},{"lineNumber":51,"author":{"gitId":"LDerpy"},"content":"","lastModifiedDate":"2022-02-18"},{"lineNumber":52,"author":{"gitId":"LDerpy"},"content":"    public static void loadTaskFromFile(TaskList tasks, String line) {","lastModifiedDate":"2022-02-24"},{"lineNumber":53,"author":{"gitId":"LDerpy"},"content":"        String[] content \u003d line.split(\"\\\\|\");","lastModifiedDate":"2022-02-18"},{"lineNumber":54,"author":{"gitId":"LDerpy"},"content":"        boolean isCompleted \u003d (\"1\".equals(content[1]));","lastModifiedDate":"2022-02-18"},{"lineNumber":55,"author":{"gitId":"LDerpy"},"content":"        switch(content[0]) {","lastModifiedDate":"2022-02-18"},{"lineNumber":56,"author":{"gitId":"LDerpy"},"content":"        case \"T\":","lastModifiedDate":"2022-02-18"},{"lineNumber":57,"author":{"gitId":"LDerpy"},"content":"            String taskDescription \u003d content[2];","lastModifiedDate":"2022-02-18"},{"lineNumber":58,"author":{"gitId":"LDerpy"},"content":"            tasks.add(new Todo(taskDescription, isCompleted));","lastModifiedDate":"2022-02-18"},{"lineNumber":59,"author":{"gitId":"LDerpy"},"content":"            break;","lastModifiedDate":"2022-02-18"},{"lineNumber":60,"author":{"gitId":"LDerpy"},"content":"        case \"D\":","lastModifiedDate":"2022-02-18"},{"lineNumber":61,"author":{"gitId":"LDerpy"},"content":"            taskDescription \u003d content[2];","lastModifiedDate":"2022-02-18"},{"lineNumber":62,"author":{"gitId":"LDerpy"},"content":"            String deadlineBy \u003d content[3];","lastModifiedDate":"2022-02-18"},{"lineNumber":63,"author":{"gitId":"LDerpy"},"content":"            tasks.add(new Deadline(taskDescription, isCompleted, deadlineBy));","lastModifiedDate":"2022-02-18"},{"lineNumber":64,"author":{"gitId":"LDerpy"},"content":"            break;","lastModifiedDate":"2022-02-18"},{"lineNumber":65,"author":{"gitId":"LDerpy"},"content":"        case \"E\":","lastModifiedDate":"2022-02-18"},{"lineNumber":66,"author":{"gitId":"LDerpy"},"content":"            taskDescription \u003d content[2];","lastModifiedDate":"2022-02-18"},{"lineNumber":67,"author":{"gitId":"LDerpy"},"content":"            String eventAt \u003d content[3];","lastModifiedDate":"2022-02-18"},{"lineNumber":68,"author":{"gitId":"LDerpy"},"content":"            tasks.add(new Event(taskDescription, isCompleted, eventAt));","lastModifiedDate":"2022-02-18"},{"lineNumber":69,"author":{"gitId":"LDerpy"},"content":"            break;","lastModifiedDate":"2022-02-18"},{"lineNumber":70,"author":{"gitId":"LDerpy"},"content":"        default:","lastModifiedDate":"2022-02-18"},{"lineNumber":71,"author":{"gitId":"LDerpy"},"content":"            break;","lastModifiedDate":"2022-02-18"},{"lineNumber":72,"author":{"gitId":"LDerpy"},"content":"        }","lastModifiedDate":"2022-02-18"},{"lineNumber":73,"author":{"gitId":"LDerpy"},"content":"    }","lastModifiedDate":"2022-02-18"},{"lineNumber":74,"author":{"gitId":"LDerpy"},"content":"","lastModifiedDate":"2022-02-18"},{"lineNumber":75,"author":{"gitId":"LDerpy"},"content":"    public static void writeTasksToFile(TaskList tasks) {","lastModifiedDate":"2022-02-24"},{"lineNumber":76,"author":{"gitId":"LDerpy"},"content":"        try {","lastModifiedDate":"2022-02-18"},{"lineNumber":77,"author":{"gitId":"LDerpy"},"content":"            FileWriter file \u003d new FileWriter(DIRECTORY_NAME + \"/\" + FILE_NAME);","lastModifiedDate":"2022-02-18"},{"lineNumber":78,"author":{"gitId":"LDerpy"},"content":"            for (int i \u003d 0; i \u003c tasks.size(); i++) {","lastModifiedDate":"2022-02-18"},{"lineNumber":79,"author":{"gitId":"LDerpy"},"content":"                file.write(tasks.get(i).getTaskCode() + \"|\" + (tasks.get(i).getCompletionStatus() ? \"1\" : \"0\")","lastModifiedDate":"2022-02-18"},{"lineNumber":80,"author":{"gitId":"LDerpy"},"content":"                        + \"|\" + tasks.get(i).getTaskDescription() + \"|\" + tasks.get(i).getExtraInfo() + \"\\n\");","lastModifiedDate":"2022-02-18"},{"lineNumber":81,"author":{"gitId":"LDerpy"},"content":"            }","lastModifiedDate":"2022-02-18"},{"lineNumber":82,"author":{"gitId":"LDerpy"},"content":"            file.close();","lastModifiedDate":"2022-02-18"},{"lineNumber":83,"author":{"gitId":"LDerpy"},"content":"        } catch (IOException e) {","lastModifiedDate":"2022-02-18"},{"lineNumber":84,"author":{"gitId":"LDerpy"},"content":"            Ui.printTextBetweenLines(\"\\t File path error! Check again!\");","lastModifiedDate":"2022-02-24"},{"lineNumber":85,"author":{"gitId":"LDerpy"},"content":"        }","lastModifiedDate":"2022-02-18"},{"lineNumber":86,"author":{"gitId":"LDerpy"},"content":"    }","lastModifiedDate":"2022-02-18"},{"lineNumber":87,"author":{"gitId":"LDerpy"},"content":"}","lastModifiedDate":"2022-02-18"}],"authorContributionMap":{"LDerpy":87}},{"path":"src/main/java/Task.java","fileType":"java","lines":[{"lineNumber":1,"author":{"gitId":"LDerpy"},"content":"public abstract class Task {","lastModifiedDate":"2022-02-14"},{"lineNumber":2,"author":{"gitId":"LDerpy"},"content":"    private String taskDescription;","lastModifiedDate":"2022-02-01"},{"lineNumber":3,"author":{"gitId":"LDerpy"},"content":"    private boolean isCompleted;","lastModifiedDate":"2022-02-18"},{"lineNumber":4,"author":{"gitId":"LDerpy"},"content":"","lastModifiedDate":"2022-02-01"},{"lineNumber":5,"author":{"gitId":"LDerpy"},"content":"    public Task(String taskDescription) {","lastModifiedDate":"2022-02-01"},{"lineNumber":6,"author":{"gitId":"LDerpy"},"content":"        setTaskDescription(taskDescription);","lastModifiedDate":"2022-02-18"},{"lineNumber":7,"author":{"gitId":"LDerpy"},"content":"        setCompleted(false);","lastModifiedDate":"2022-02-18"},{"lineNumber":8,"author":{"gitId":"LDerpy"},"content":"    }","lastModifiedDate":"2022-02-18"},{"lineNumber":9,"author":{"gitId":"LDerpy"},"content":"","lastModifiedDate":"2022-02-18"},{"lineNumber":10,"author":{"gitId":"LDerpy"},"content":"    public Task(String taskDescription, boolean isCompleted) {","lastModifiedDate":"2022-02-18"},{"lineNumber":11,"author":{"gitId":"LDerpy"},"content":"        setTaskDescription(taskDescription);","lastModifiedDate":"2022-02-18"},{"lineNumber":12,"author":{"gitId":"LDerpy"},"content":"        setCompleted(isCompleted);","lastModifiedDate":"2022-02-18"},{"lineNumber":13,"author":{"gitId":"LDerpy"},"content":"    }","lastModifiedDate":"2022-02-01"},{"lineNumber":14,"author":{"gitId":"LDerpy"},"content":"","lastModifiedDate":"2022-02-01"},{"lineNumber":15,"author":{"gitId":"LDerpy"},"content":"    public String getTaskDescription() {","lastModifiedDate":"2022-02-01"},{"lineNumber":16,"author":{"gitId":"LDerpy"},"content":"        return taskDescription;","lastModifiedDate":"2022-02-01"},{"lineNumber":17,"author":{"gitId":"LDerpy"},"content":"    }","lastModifiedDate":"2022-02-01"},{"lineNumber":18,"author":{"gitId":"LDerpy"},"content":"","lastModifiedDate":"2022-02-01"},{"lineNumber":19,"author":{"gitId":"LDerpy"},"content":"    public void setTaskDescription(String taskDescription) {","lastModifiedDate":"2022-02-18"},{"lineNumber":20,"author":{"gitId":"LDerpy"},"content":"        this.taskDescription \u003d taskDescription;","lastModifiedDate":"2022-02-18"},{"lineNumber":21,"author":{"gitId":"LDerpy"},"content":"    }","lastModifiedDate":"2022-02-01"},{"lineNumber":22,"author":{"gitId":"LDerpy"},"content":"","lastModifiedDate":"2022-02-01"},{"lineNumber":23,"author":{"gitId":"LDerpy"},"content":"    public boolean getCompletionStatus() {","lastModifiedDate":"2022-02-18"},{"lineNumber":24,"author":{"gitId":"LDerpy"},"content":"        return isCompleted;","lastModifiedDate":"2022-02-18"},{"lineNumber":25,"author":{"gitId":"LDerpy"},"content":"    }","lastModifiedDate":"2022-02-01"},{"lineNumber":26,"author":{"gitId":"LDerpy"},"content":"","lastModifiedDate":"2022-02-01"},{"lineNumber":27,"author":{"gitId":"LDerpy"},"content":"    public void setCompleted(boolean isCompleted) {","lastModifiedDate":"2022-02-18"},{"lineNumber":28,"author":{"gitId":"LDerpy"},"content":"        this.isCompleted \u003d isCompleted;","lastModifiedDate":"2022-02-18"},{"lineNumber":29,"author":{"gitId":"LDerpy"},"content":"    }","lastModifiedDate":"2022-02-01"},{"lineNumber":30,"author":{"gitId":"LDerpy"},"content":"","lastModifiedDate":"2022-02-01"},{"lineNumber":31,"author":{"gitId":"LDerpy"},"content":"    public String toString() {","lastModifiedDate":"2022-02-01"},{"lineNumber":32,"author":{"gitId":"LDerpy"},"content":"        return \"[\" + (isCompleted ? \"X\" : \" \") + \"] \" + getTaskDescription();","lastModifiedDate":"2022-02-02"},{"lineNumber":33,"author":{"gitId":"LDerpy"},"content":"    }","lastModifiedDate":"2022-02-01"},{"lineNumber":34,"author":{"gitId":"LDerpy"},"content":"","lastModifiedDate":"2022-02-18"},{"lineNumber":35,"author":{"gitId":"LDerpy"},"content":"    public abstract String getTaskCode();","lastModifiedDate":"2022-02-18"},{"lineNumber":36,"author":{"gitId":"LDerpy"},"content":"","lastModifiedDate":"2022-02-18"},{"lineNumber":37,"author":{"gitId":"LDerpy"},"content":"    public abstract String getExtraInfo();","lastModifiedDate":"2022-02-18"},{"lineNumber":38,"author":{"gitId":"LDerpy"},"content":"}","lastModifiedDate":"2022-02-01"}],"authorContributionMap":{"LDerpy":38}},{"path":"src/main/java/TaskList.java","fileType":"java","lines":[{"lineNumber":1,"author":{"gitId":"LDerpy"},"content":"import java.util.ArrayList;","lastModifiedDate":"2022-02-24"},{"lineNumber":2,"author":{"gitId":"LDerpy"},"content":"","lastModifiedDate":"2022-02-24"},{"lineNumber":3,"author":{"gitId":"LDerpy"},"content":"public class TaskList {","lastModifiedDate":"2022-02-24"},{"lineNumber":4,"author":{"gitId":"LDerpy"},"content":"    private final ArrayList\u003cTask\u003e tasks \u003d new ArrayList\u003c\u003e();","lastModifiedDate":"2022-02-24"},{"lineNumber":5,"author":{"gitId":"LDerpy"},"content":"","lastModifiedDate":"2022-02-24"},{"lineNumber":6,"author":{"gitId":"LDerpy"},"content":"    public void add(Task task) {","lastModifiedDate":"2022-02-24"},{"lineNumber":7,"author":{"gitId":"LDerpy"},"content":"        tasks.add(task);","lastModifiedDate":"2022-02-24"},{"lineNumber":8,"author":{"gitId":"LDerpy"},"content":"    }","lastModifiedDate":"2022-02-24"},{"lineNumber":9,"author":{"gitId":"LDerpy"},"content":"","lastModifiedDate":"2022-02-24"},{"lineNumber":10,"author":{"gitId":"LDerpy"},"content":"    public int size() {","lastModifiedDate":"2022-02-24"},{"lineNumber":11,"author":{"gitId":"LDerpy"},"content":"        return tasks.size();","lastModifiedDate":"2022-02-24"},{"lineNumber":12,"author":{"gitId":"LDerpy"},"content":"    }","lastModifiedDate":"2022-02-24"},{"lineNumber":13,"author":{"gitId":"LDerpy"},"content":"","lastModifiedDate":"2022-02-24"},{"lineNumber":14,"author":{"gitId":"LDerpy"},"content":"    public Task get(int index) {","lastModifiedDate":"2022-02-24"},{"lineNumber":15,"author":{"gitId":"LDerpy"},"content":"        return tasks.get(index);","lastModifiedDate":"2022-02-24"},{"lineNumber":16,"author":{"gitId":"LDerpy"},"content":"    }","lastModifiedDate":"2022-02-24"},{"lineNumber":17,"author":{"gitId":"LDerpy"},"content":"","lastModifiedDate":"2022-02-24"},{"lineNumber":18,"author":{"gitId":"LDerpy"},"content":"    public void remove(int index) {","lastModifiedDate":"2022-02-24"},{"lineNumber":19,"author":{"gitId":"LDerpy"},"content":"        tasks.remove(index);","lastModifiedDate":"2022-02-24"},{"lineNumber":20,"author":{"gitId":"LDerpy"},"content":"    }","lastModifiedDate":"2022-02-24"},{"lineNumber":21,"author":{"gitId":"LDerpy"},"content":"}","lastModifiedDate":"2022-02-24"}],"authorContributionMap":{"LDerpy":21}},{"path":"src/main/java/Todo.java","fileType":"java","lines":[{"lineNumber":1,"author":{"gitId":"LDerpy"},"content":"public class Todo extends Task {","lastModifiedDate":"2022-02-02"},{"lineNumber":2,"author":{"gitId":"LDerpy"},"content":"    private static final String TASK_CODE \u003d \"T\";","lastModifiedDate":"2022-02-18"},{"lineNumber":3,"author":{"gitId":"LDerpy"},"content":"","lastModifiedDate":"2022-02-18"},{"lineNumber":4,"author":{"gitId":"LDerpy"},"content":"    public Todo(String taskDescription) {","lastModifiedDate":"2022-02-02"},{"lineNumber":5,"author":{"gitId":"LDerpy"},"content":"        super(taskDescription);","lastModifiedDate":"2022-02-02"},{"lineNumber":6,"author":{"gitId":"LDerpy"},"content":"    }","lastModifiedDate":"2022-02-02"},{"lineNumber":7,"author":{"gitId":"LDerpy"},"content":"","lastModifiedDate":"2022-02-02"},{"lineNumber":8,"author":{"gitId":"LDerpy"},"content":"    public Todo(String taskDescription, boolean isCompleted) {","lastModifiedDate":"2022-02-18"},{"lineNumber":9,"author":{"gitId":"LDerpy"},"content":"        super(taskDescription, isCompleted);","lastModifiedDate":"2022-02-18"},{"lineNumber":10,"author":{"gitId":"LDerpy"},"content":"    }","lastModifiedDate":"2022-02-18"},{"lineNumber":11,"author":{"gitId":"LDerpy"},"content":"","lastModifiedDate":"2022-02-18"},{"lineNumber":12,"author":{"gitId":"LDerpy"},"content":"    @Override","lastModifiedDate":"2022-02-18"},{"lineNumber":13,"author":{"gitId":"LDerpy"},"content":"    public String getTaskCode() {","lastModifiedDate":"2022-02-18"},{"lineNumber":14,"author":{"gitId":"LDerpy"},"content":"        return TASK_CODE;","lastModifiedDate":"2022-02-18"},{"lineNumber":15,"author":{"gitId":"LDerpy"},"content":"    }","lastModifiedDate":"2022-02-18"},{"lineNumber":16,"author":{"gitId":"LDerpy"},"content":"","lastModifiedDate":"2022-02-18"},{"lineNumber":17,"author":{"gitId":"LDerpy"},"content":"    @Override","lastModifiedDate":"2022-02-18"},{"lineNumber":18,"author":{"gitId":"LDerpy"},"content":"    public String getExtraInfo() {","lastModifiedDate":"2022-02-18"},{"lineNumber":19,"author":{"gitId":"LDerpy"},"content":"        return \"\";","lastModifiedDate":"2022-02-18"},{"lineNumber":20,"author":{"gitId":"LDerpy"},"content":"    }","lastModifiedDate":"2022-02-18"},{"lineNumber":21,"author":{"gitId":"LDerpy"},"content":"","lastModifiedDate":"2022-02-18"},{"lineNumber":22,"author":{"gitId":"LDerpy"},"content":"    @Override","lastModifiedDate":"2022-02-02"},{"lineNumber":23,"author":{"gitId":"LDerpy"},"content":"    public String toString() {","lastModifiedDate":"2022-02-02"},{"lineNumber":24,"author":{"gitId":"LDerpy"},"content":"        return \"[\" + getTaskCode() + \"]\" + super.toString() + \"\\n\";","lastModifiedDate":"2022-02-18"},{"lineNumber":25,"author":{"gitId":"LDerpy"},"content":"    }","lastModifiedDate":"2022-02-02"},{"lineNumber":26,"author":{"gitId":"LDerpy"},"content":"}","lastModifiedDate":"2022-02-02"}],"authorContributionMap":{"LDerpy":26}},{"path":"src/main/java/Ui.java","fileType":"java","lines":[{"lineNumber":1,"author":{"gitId":"LDerpy"},"content":"public class Ui {","lastModifiedDate":"2022-02-24"},{"lineNumber":2,"author":{"gitId":"LDerpy"},"content":"","lastModifiedDate":"2022-02-24"},{"lineNumber":3,"author":{"gitId":"LDerpy"},"content":"    public static void printHorizontalLine() {","lastModifiedDate":"2022-02-24"},{"lineNumber":4,"author":{"gitId":"LDerpy"},"content":"        System.out.println(Message.HORIZONTAL_LINE);","lastModifiedDate":"2022-02-24"},{"lineNumber":5,"author":{"gitId":"LDerpy"},"content":"    }","lastModifiedDate":"2022-02-24"},{"lineNumber":6,"author":{"gitId":"LDerpy"},"content":"","lastModifiedDate":"2022-02-24"},{"lineNumber":7,"author":{"gitId":"LDerpy"},"content":"    public static void printTextBetweenLines(String text) {","lastModifiedDate":"2022-02-24"},{"lineNumber":8,"author":{"gitId":"LDerpy"},"content":"        printHorizontalLine();","lastModifiedDate":"2022-02-24"},{"lineNumber":9,"author":{"gitId":"LDerpy"},"content":"        System.out.print(text);","lastModifiedDate":"2022-02-24"},{"lineNumber":10,"author":{"gitId":"LDerpy"},"content":"        printHorizontalLine();","lastModifiedDate":"2022-02-24"},{"lineNumber":11,"author":{"gitId":"LDerpy"},"content":"    }","lastModifiedDate":"2022-02-24"},{"lineNumber":12,"author":{"gitId":"LDerpy"},"content":"","lastModifiedDate":"2022-02-24"},{"lineNumber":13,"author":{"gitId":"LDerpy"},"content":"    public static void startDuke() {","lastModifiedDate":"2022-02-24"},{"lineNumber":14,"author":{"gitId":"LDerpy"},"content":"        System.out.println(Message.GREET_MESSAGE);","lastModifiedDate":"2022-02-24"},{"lineNumber":15,"author":{"gitId":"LDerpy"},"content":"    }","lastModifiedDate":"2022-02-24"},{"lineNumber":16,"author":{"gitId":"LDerpy"},"content":"","lastModifiedDate":"2022-02-24"},{"lineNumber":17,"author":{"gitId":"LDerpy"},"content":"    public static void endDuke() {","lastModifiedDate":"2022-02-24"},{"lineNumber":18,"author":{"gitId":"LDerpy"},"content":"        printHorizontalLine();","lastModifiedDate":"2022-02-24"},{"lineNumber":19,"author":{"gitId":"LDerpy"},"content":"        System.out.println(Message.GOODBYE_MESSAGE);","lastModifiedDate":"2022-02-24"},{"lineNumber":20,"author":{"gitId":"LDerpy"},"content":"        printHorizontalLine();","lastModifiedDate":"2022-02-24"},{"lineNumber":21,"author":{"gitId":"LDerpy"},"content":"    }","lastModifiedDate":"2022-02-24"},{"lineNumber":22,"author":{"gitId":"LDerpy"},"content":"}","lastModifiedDate":"2022-02-24"}],"authorContributionMap":{"LDerpy":22}}]
